hfstudio/__init__.py
hfstudio/__main__.py
hfstudio/cli.py
hfstudio/server.py
hfstudio/static/index.html
hfstudio/static/_app/env.js
hfstudio/static/_app/version.json
hfstudio/static/_app/immutable/assets/0.DXU3PXrR.css
hfstudio/static/_app/immutable/assets/2.BoAMr1TJ.css
hfstudio/static/_app/immutable/chunks/BF3xBGh8.js
hfstudio/static/_app/immutable/chunks/CPkOsRcw.js
hfstudio/static/_app/immutable/chunks/IHki7fMi.js
hfstudio/static/_app/immutable/entry/app.BXUCRyKe.js
hfstudio/static/_app/immutable/entry/start.18rYT4MG.js
hfstudio/static/_app/immutable/nodes/0.8tK7co2W.js
hfstudio/static/_app/immutable/nodes/1.C8fax3Yl.js
hfstudio/static/_app/immutable/nodes/2.D1a2TSEw.js
hfstudio/static/assets/hf-logo.png
hfstudio/static/assets/hf-studio-logo.png
hfstudio/static/samples/harvard.wav
hfstudio/static/voices/andrew.mp3
hfstudio/static/voices/fairy.mp3
hfstudio/static/voices/lily.mp3
hfstudio/static/voices/pirate.mp3
hfstudio-0.1.3.dist-info/METADATA
hfstudio-0.1.3.dist-info/WHEEL
hfstudio-0.1.3.dist-info/entry_points.txt
hfstudio-0.1.3.dist-info/top_level.txt
hfstudio-0.1.3.dist-info/RECORD
