Metadata-Version: 2.4
Name: hfstudio
Version: 0.1.3
Summary: Local and API-based Text-to-Speech Studio
Author: HFStudio Team
License: MIT
Project-URL: Homepage, https://github.com/yourusername/hfstudio
Project-URL: Repository, https://github.com/yourusername/hfstudio
Classifier: Development Status :: 3 - Alpha
Classifier: Intended Audience :: Developers
Classifier: Topic :: Multimedia :: Sound/Audio :: Speech
Classifier: License :: OSI Approved :: MIT License
Classifier: Programming Language :: Python :: 3
Classifier: Programming Language :: Python :: 3.8
Classifier: Programming Language :: Python :: 3.9
Classifier: Programming Language :: Python :: 3.10
Classifier: Programming Language :: Python :: 3.11
Requires-Python: >=3.8
Requires-Dist: fastapi>=0.100.0
Requires-Dist: uvicorn[standard]>=0.20.0
Requires-Dist: typer[all]>=0.9.0
Requires-Dist: pydantic>=2.0.0
Requires-Dist: huggingface-hub>=0.20.0
Requires-Dist: httpx>=0.25.0
Requires-Dist: numpy>=1.21.0
Requires-Dist: soundfile>=0.12.0
Provides-Extra: dev
Requires-Dist: pytest>=7.0.0; extra == "dev"
Requires-Dist: pytest-asyncio>=0.21.0; extra == "dev"
Requires-Dist: black>=23.0.0; extra == "dev"
Requires-Dist: ruff>=0.1.0; extra == "dev"
